breezy/plugins/difftacular/__init__.py
breezy/plugins/difftacular/command.py
breezy/plugins/difftacular/generate_diff.py
breezy/plugins/difftacular/tests/__init__.py
breezy/plugins/difftacular/tests/test_generate_diff.py
difftacular-0.1.dist-info/METADATA
difftacular-0.1.dist-info/WHEEL
difftacular-0.1.dist-info/top_level.txt
difftacular-0.1.dist-info/RECORD
