Metadata-Version: 2.1
Name: difftacular
Version: 0.1
Summary: Extra diff-generation commands for Bazaar
Home-page: https://launchpad.net/difftacular
Author: Aaron Bentley
Maintainer: The Launchpad developers
Maintainer-email: launchpad-dev@lists.launchpad.net
License: GPL-2.0
Classifier: Environment :: Plugins
Classifier: License :: OSI Approved :: GNU General Public License v2 (GPLv2)
Classifier: Programming Language :: Python
Classifier: Programming Language :: Python :: 2
Classifier: Programming Language :: Python :: 3
Classifier: Topic :: Software Development :: Version Control
Requires-Dist: breezy
